MANIFEST.in
README.rst
setup.py
extra_keras_utils/__init__.py
extra_keras_utils/__version__.py
extra_keras_utils/get_gpus_number.py
extra_keras_utils/is_gpu_available.py
extra_keras_utils/is_multi_gpu.py
extra_keras_utils/set_seed.py
extra_keras_utils.egg-info/PKG-INFO
extra_keras_utils.egg-info/SOURCES.txt
extra_keras_utils.egg-info/dependency_links.txt
extra_keras_utils.egg-info/requires.txt
extra_keras_utils.egg-info/top_level.txt