Metadata-Version: 2.1
Name: extra-keras-utils
Version: 1.0.4
Summary: Python package collecting commonly used snippets for the Keras library.
Home-page: https://github.com/LucaCappelletti94/extra_keras_utils
Author: Luca Cappelletti
Author-email: cappelletti.luca94@gmail.com
License: MIT
Platform: UNKNOWN
Classifier: Development Status :: 3 - Alpha
Classifier: License :: OSI Approved :: MIT License
Classifier: Programming Language :: Python :: 3
Provides-Extra: test
